gentropy/__init__.py
gentropy/biosample_index.py
gentropy/cli.py
gentropy/colocalisation.py
gentropy/config.py
gentropy/credible_set_qc.py
gentropy/eqtl_catalogue.py
gentropy/finemapping_simulations.py
gentropy/finngen_finemapping_ingestion.py
gentropy/finngen_studies.py
gentropy/finngen_sumstat_preprocess.py
gentropy/finngen_ukb_mvp_meta.py
gentropy/foldx_ingestion.py
gentropy/gnomad_ingestion.py
gentropy/gwas_catalog_study_curation.py
gentropy/gwas_catalog_study_index.py
gentropy/gwas_catalog_sumstat_preprocess.py
gentropy/gwas_catalog_top_hits.py
gentropy/intervals.py
gentropy/l2g.py
gentropy/ld_based_clumping.py
gentropy/locus_breaker_clumping.py
gentropy/lof_curation_ingestion.py
gentropy/pics.py
gentropy/py.typed
gentropy/study_locus_validation.py
gentropy/study_validation.py
gentropy/sumstat_qc_step.py
gentropy/susie_finemapper.py
gentropy/ukb_ppp_eur_sumstat_preprocess.py
gentropy/variant_index.py
gentropy/window_based_clumping.py
gentropy/assets/__init__.py
gentropy/assets/variant_consequences.py
gentropy/assets/data/__init__.py
gentropy/assets/data/gwas_pValueText_map.json
gentropy/assets/data/gwas_population_2_LD_panel_map.json
gentropy/assets/schemas/__init__.py
gentropy/assets/schemas/amino_acid_variants.json
gentropy/assets/schemas/biosample_index.json
gentropy/assets/schemas/colocalisation.json
gentropy/assets/schemas/intervals.json
gentropy/assets/schemas/l2g_feature.json
gentropy/assets/schemas/l2g_gold_standard.json
gentropy/assets/schemas/l2g_predictions.json
gentropy/assets/schemas/ld_index.json
gentropy/assets/schemas/pairwise_ld.json
gentropy/assets/schemas/study_index.json
gentropy/assets/schemas/study_locus.json
gentropy/assets/schemas/study_locus_overlap.json
gentropy/assets/schemas/summary_statistics.json
gentropy/assets/schemas/summary_statistics_qc.json
gentropy/assets/schemas/target_index.json
gentropy/assets/schemas/variant_direction.json
gentropy/assets/schemas/variant_index.json
gentropy/assets/schemas/vep_json_output.json
gentropy-3.1.1.dist-info/METADATA
gentropy-3.1.1.dist-info/WHEEL
gentropy-3.1.1.dist-info/entry_points.txt
gentropy-3.1.1.dist-info/licenses/LICENSE.md
gentropy-3.1.1.dist-info/RECORD
