Metadata-Version: 2.4
Name: gentropy
Version: 3.1.1
Summary: Open Targets python framework for post-GWAS analysis
Project-URL: Source, https://github.com/opentargets/gentropy
Project-URL: Bug Tracker, http://github.com/opentargets/issues
Project-URL: Funding, https://www.opentargets.org
Project-URL: Documentation, https://opentargets.github.io/gentropy/
Author-email: Open Targets core team <data@opentargets.org>
License-Expression: Apache-2.0
License-File: LICENSE.md
Classifier: Programming Language :: Python :: 3.11
Classifier: Programming Language :: Python :: 3.12
Classifier: Programming Language :: Python :: 3.13
Requires-Python: <3.14,>=3.11
Requires-Dist: google-cloud-secret-manager<2.26.0,>=2.12.6
Requires-Dist: google-cloud-storage<3.4.0,>=2.14.0
Requires-Dist: hail>=0.2.136
Requires-Dist: huggingface-hub>=0.27.1
Requires-Dist: hydra-core<1.4.0,>=1.3.2
Requires-Dist: matplotlib<3.11.0,>=3.10.0
Requires-Dist: numpy>=2.3.0
Requires-Dist: omegaconf<2.4.0,>=2.3.0
Requires-Dist: pandas[gcp,parquet]<2.4.0,>=2.2.3
Requires-Dist: pyliftover<0.5.0,>=0.4.1
Requires-Dist: pyspark[pandas-on-spark]<3.6,>=3.5.0
Requires-Dist: scikit-learn<1.8.0,>=1.6.1
Requires-Dist: scipy<1.16.0,>=1.11.4
Requires-Dist: shap>=0.50.0
Requires-Dist: skops<0.14.0,>=0.13.0
Requires-Dist: wandb<0.23.0,>=0.19.4
Requires-Dist: xgboost-cpu>=3.0.4; (platform_machine == 'amd64' and sys_platform != 'darwin') or (platform_machine == 'x86_64' and sys_platform != 'darwin')
Requires-Dist: xgboost>=3.0.4; platform_machine == 'aarch64' or platform_machine == 'arm64'
Requires-Dist: xgboost>=3.0.4; platform_machine == 'x86_64' and sys_platform == 'darwin'
